layered_vision/__init__.py
layered_vision/__main__.py
layered_vision/app.py
layered_vision/cli.py
layered_vision/config.py
layered_vision/resolved_config.py
layered_vision/filters/__init__.py
layered_vision/filters/api.py
layered_vision/filters/bilateral.py
layered_vision/filters/bodypix.py
layered_vision/filters/composite.py
layered_vision/filters/fill.py
layered_vision/filters/invert.py
layered_vision/filters/mp_selfie_segmentation.py
layered_vision/filters/multiply.py
layered_vision/filters/warp_perspective.py
layered_vision/sinks/__init__.py
layered_vision/sinks/api.py
layered_vision/sinks/v4l2.py
layered_vision/sinks/web.py
layered_vision/sources/__init__.py
layered_vision/sources/api.py
layered_vision/sources/fill.py
layered_vision/sources/mss.py
layered_vision/sources/youtube.py
layered_vision/utils/__init__.py
layered_vision/utils/colors.py
layered_vision/utils/dist.py
layered_vision/utils/image.py
layered_vision/utils/io.py
layered_vision/utils/lazy_image.py
layered_vision/utils/opencv.py
layered_vision/utils/path.py
layered_vision/utils/timer.py
layered_vision/utils/v4l2.py
layered_vision-0.0.7.dist-info/LICENSE
layered_vision-0.0.7.dist-info/METADATA
layered_vision-0.0.7.dist-info/WHEEL
layered_vision-0.0.7.dist-info/top_level.txt
layered_vision-0.0.7.dist-info/RECORD
