Metadata-Version: 2.1
Name: layered-vision
Version: 0.0.7
Summary: Compose final output(s), out of layers of images, videos or similar.
Home-page: https://github.com/de-code/layered-vision
Author: Daniel Ecer
License: UNKNOWN
Platform: UNKNOWN
Classifier: Programming Language :: Python :: 3
Classifier: License :: OSI Approved :: MIT License
Classifier: Operating System :: OS Independent
Requires-Dist: Flask (==2.2.2)
Requires-Dist: mediapipe (>=0.8.7.1)
Requires-Dist: mss (==7.0.1)
Requires-Dist: numpy (<1.22.0,>=1.19.3)
Requires-Dist: opencv-python (==4.7.0.68)
Requires-Dist: pafy (==0.5.5)
Requires-Dist: pyfakewebcam (==0.1.0)
Requires-Dist: PyYAML (==6.0)
Requires-Dist: tensorflow (==2.11.0)
Requires-Dist: tf-bodypix[tfjs] (==0.4.2)
Requires-Dist: youtube-dl (==2021.12.17)
